ilpy/__init__.py
ilpy/_components.py
ilpy/_constants.py
ilpy/_functional.py
ilpy/_solver.py
ilpy/event_data.py
ilpy/expressions.py
ilpy/py.typed
ilpy/solver_backends/__init__.py
ilpy/solver_backends/_base.py
ilpy/solver_backends/_gurobi.py
ilpy/solver_backends/_scip.py
ilpy-0.5.1.dist-info/METADATA
ilpy-0.5.1.dist-info/WHEEL
ilpy-0.5.1.dist-info/licenses/LICENSE
ilpy-0.5.1.dist-info/RECORD
