Metadata-Version: 2.4
Name: ilpy
Version: 0.5.1
Summary: Unified API for ILP solvers.
Project-URL: homepage, https://github.com/funkelab/ilpy
Project-URL: repository, https://github.com/funkelab/ilpy
Author-email: Jan Funke <funkej@janelia.hhmi.org>, Talley Lambert <talley.lambert@gmail.com>
License: MIT
License-File: LICENSE
Classifier: Development Status :: 3 - Alpha
Classifier: License :: OSI Approved :: BSD License
Classifier: Programming Language :: Python :: 3
Classifier: Programming Language :: Python :: 3.9
Classifier: Programming Language :: Python :: 3.10
Classifier: Programming Language :: Python :: 3.11
Classifier: Programming Language :: Python :: 3.12
Classifier: Programming Language :: Python :: 3.13
Classifier: Typing :: Typed
Requires-Python: >=3.9
Requires-Dist: pyscipopt
Provides-Extra: dev
Requires-Dist: gurobipy; extra == 'dev'
Requires-Dist: ipython; extra == 'dev'
Requires-Dist: mypy; extra == 'dev'
Requires-Dist: numpy; extra == 'dev'
Requires-Dist: pre-commit; extra == 'dev'
Requires-Dist: pyscipopt; extra == 'dev'
Requires-Dist: pytest; extra == 'dev'
Requires-Dist: pytest-cov; extra == 'dev'
Requires-Dist: ruff; extra == 'dev'
Provides-Extra: docs
Requires-Dist: numpy; extra == 'docs'
Requires-Dist: sphinx; extra == 'docs'
Requires-Dist: sphinx-autodoc-typehints; extra == 'docs'
Requires-Dist: sphinx-rtd-theme; extra == 'docs'
Provides-Extra: gurobi
Requires-Dist: gurobipy; extra == 'gurobi'
Provides-Extra: scip
Requires-Dist: pyscipopt; extra == 'scip'
Provides-Extra: test
Requires-Dist: gurobipy; extra == 'test'
Requires-Dist: numpy; extra == 'test'
Requires-Dist: pyscipopt; extra == 'test'
Requires-Dist: pytest; extra == 'test'
Requires-Dist: pytest-cov; extra == 'test'
